{
    "Black":[
        "Black",
        "Charcoal",
        "Jet Black",
        "Licorice",
        "Matte Black",
        "Onyx"
    ],
    "Blue":[
        "Aqua",
        "Azure",
        "Baby Blue",
        "Blue",
        "Blue Gray",
        "Blue Green",
        "Bright Blue",
        "Cadet Blue",
        "Cobalt Blue",
        "Cornflower Blue",
        "Cyan",
        "Dark Blue",
        "Denim",
        "Egyptian Blue",
        "Electric Blue",
        "Glaucous",
        "Jade",
        "Indigo",
        "Iris",
        "Light Blue",
        "Midnight Blue",
        "Navy Blue",
        "Neon Blue",
        "Pastel Blue",
        "Periwinkle",
        "Powder Blue",
        "Robin Egg Blue",
        "Royal Blue",
        "Sapphire Blue",
        "Seafoam Green",
        "Sky Blue",
        "Steel Blue",
        "Teal",
        "Turquoise",
        "Ultramarine",
        "Verdigris",
        "Zaffre"
    ],
    "Brown":[
        "Almond",
        "Bronze",
        "Brown",
        "Buff",
        "Burnt Sienna",
        "Burnt Umber",
        "Camel",
        "Chestnut",
        "Chocolate",
        "Cinnamon",
        "Coffee",
        "Cognac",
        "Copper",
        "Cordovan",
        "Dark Brown",
        "Dark Tan",
        "Desert",
        "Ecru",
        "Fallow",
        "Fawn",
        "Golden Brown",
        "Khaki",
        "Light Brown",
        "Mahogany",
        "Mocha",
        "Nude",
        "Ochre",
        "Puce",
        "Red Brown",
        "Russet",
        "Saddle Brown",
        "Sand",
        "Sienna",
        "Tan",
        "Taupe",
        "Wheat"
    ],
    "Grey":[
        "Ash Gray",
        "Blue Gray",
        "Charcoal",
        "Dark Gray",
        "Glaucous",
        "Gray",
        "Gunmetal Gray",
        "Light Gray",
        "Pewter",
        "Platinum",
        "Silver",
        "Slate Gray",
        "Smoke",
        "Steel Gray"
    ],
    "Green":[
        "Aquamarine",
        "Army Green",
        "Blue Green",
        "Bright Green",
        "Cadmium Green",
        "Celadon",
        "Chartreuse",
        "Dark Green",
        "Emerald Green",
        "Eucalyptus",
        "Fern Green",
        "Forest Green",
        "Grass Green",
        "Green",
        "Hunter Green",
        "Jade",
        "Jungle Green",
        "Kelly Green",
        "Light Green",
        "Lime Green",
        "Lincoln Green",
        "Malachite",
        "Mint Green",
        "Moss Green",
        "Neon Green",
        "Nyanza",
        "Olive Green",
        "Pastel Green",
        "Pear",
        "Peridot",
        "Pistachio",
        "Sage Green",
        "Sea Green",
        "Seafoam Green",
        "Shamrock Green",
        "Spring Green",
        "Teal",
        "Verdigris",
        "Viridian"
    ],
    "Orange":[
        "Amber",
        "Apricot",
        "Bisque",
        "Bright Orange",
        "Burnt Orange",
        "Burnt Sienna",
        "Butterscotch",
        "Cadmium Orange",
        "Coral",
        "Dark Orange",
        "Gamboge",
        "Light Orange",
        "Mango",
        "Neon Orange",
        "Orange",
        "Pastel Orange",
        "Peach",
        "Persimmon",
        "Pink Orange",
        "Poppy",
        "Pumpkin Orange",
        "Red Orange",
        "Sunset Orange",
        "Tangerine",
        "Terra Cotta",
        "Yellow Orange"
    ],
    "Purple":[
        "Amaranth",
        "Bright Purple",
        "Byzantium",
        "Dark Purple",
        "Eggplant",
        "Iris",
        "Lavender",
        "Light Purple",
        "Light Violet",
        "Lilac",
        "Mauve",
        "Mauve Taupe",
        "Mulberry",
        "Orchid",
        "Pastel Purple",
        "Plum",
        "Puce",
        "Purple",
        "Quartz",
        "Thistle",
        "Tyrian Purple",
        "Violet",
        "Wine",
        "Wisteria"
    ],
    "Red":[
        "Blood Red",
        "Brick Red",
        "Bright Red",
        "Burgundy",
        "Cadmium Red",
        "Cardinal Red",
        "Carmine",
        "Cerise",
        "Cherry",
        "Chestnut",
        "Claret",
        "Coral Pink",
        "Cordovan",
        "Crimson",
        "Dark Pink",
        "Dark Red",
        "Dusty Rose",
        "Falu Red",
        "Fuchsia",
        "Garnet",
        "Hot Pink",
        "Light Pink",
        "Magenta",
        "Maroon",
        "Marsala",
        "Millennial Pink",
        "Mulberry",
        "Neon Pink",
        "Neon Red",
        "Oxblood",
        "Pastel Pink",
        "Pastel Red",
        "Pink",
        "Poppy",
        "Puce",
        "Raspberry",
        "Red",
        "Red Brown",
        "Red Ochre",
        "Red Orange",
        "Red Purple",
        "Rose",
        "Rose Gold",
        "Rose Red",
        "Ruby Red",
        "Russet",
        "Salmon",
        "Scarlet",
        "Seashell",
        "Terra Cotta",
        "Tuscan Red",
        "Venetian Red",
        "Vermillion",
        "Watermelon Pink",
        "Wine"
    ],
    "Yellow":[
        "Bright Yellow",
        "Cadmium Yellow",
        "Canary Yellow",
        "Citrine",
        "Cornsilk",
        "Cream",
        "Dark Yellow",
        "Ecru",
        "Flax",
        "Gold",
        "Golden Yellow",
        "Goldenrod",
        "Icterine",
        "Jasmine",
        "Lemon Yellow",
        "Maize",
        "Mustard Yellow",
        "Naples Yellow",
        "Pastel Yellow",
        "Saffron",
        "Vegas Gold",
        "Yellow",
        "Yellow Orange"
    ]
}